{
    "telepistons": {
	"squish":"false",
	"particles":"4",
	"squishedScale": [ 1, 1, 0 ]
    },
    "textures": {
        "piston_arm": "telepistons:block/piston_arm"
    },
    "display": {
        "gui": {
            "rotation": [ 30, 45, 0 ],
            "translation": [ 0, 0, 0 ],
            "scale": [ 0.625, 0.625, 0.625 ]
        },
        "ground": {
            "rotation": [ 0, 0, 0 ],
            "translation": [ 0, 3, 0 ],
            "scale": [ 0.25, 0.25, 0.25 ]
        },
        "fixed": {
            "rotation": [ 0, 180, 0 ],
            "translation": [ 0, 0, 0 ],
            "scale": [ 1, 1, 1 ]
        },
        "head": {
            "rotation": [ 0, 180, 0 ],
            "translation": [ 0, 0, 0 ],
            "scale": [ 1, 1, 1 ]
        },
        "firstperson_righthand": {
            "rotation": [ 0, 315, 0 ],
            "translation": [ 0, 2.5, 0 ],
            "scale": [ 0.4, 0.4, 0.4 ]
        },
        "thirdperson_righthand": {
            "rotation": [ 75, 315, 0 ],
            "translation": [ 0, 2.5, 0 ],
            "scale": [ 0.375, 0.375, 0.375 ]
        }
    },
    "elements": [
        {
            "name": "Arm",
            "from": [ 5, 5, 12 ], 
            "to": [ 11, 11, 20 ], 
            "faces": {
                "north": { "texture": "#piston_arm", "uv": [ 6, 10, 12, 16 ] },
                "east": { "texture": "#piston_arm", "uv": [ 0, 8, 6, 16 ], "rotation": 90 },
                "west": { "texture": "#piston_arm", "uv": [ 0, 8, 6, 16 ], "rotation": 270 },
                "up": { "texture": "#piston_arm", "uv": [ 0, 8, 6, 16 ] },
                "down": { "texture": "#piston_arm", "uv": [ 0, 8, 6, 16 ], "rotation": 180 }
            }
        }
    ]
}